<?xml version="1.0" encoding="UTF-8"?>
<MIAP>
  <MIAP-Header>
    <TransactionID>20110909090909000001</TransactionID>
    <Version>1.0</Version>
    <MessageName>ApplyListResp</MessageName>
    <TestFlag>1</TestFlag>
    <ReturnCode>00</ReturnCode>
    <ReturnMessage>
    </ReturnMessage>
  </MIAP-Header>
  <MIAP-Body>
    <ApplyListResp>
      <GROUPID>100001</GROUPID>
      <GROUPNAME>111</GROUPNAME>
      <MOBILENO>15501622816</MOBILENO>
      <HEADPORTRAIT>
      </HEADPORTRAIT>
    </ApplyListResp>
  </MIAP-Body>
</MIAP>